hermeskit/__init__.py
hermeskit/exceptions/__init__.py
hermeskit/metrics/__init__.py
hermeskit/metrics/_report.py
hermeskit/metrics/setup.py
hermeskit/metrics/tests/__init__.py
hermeskit/metrics/tests/test_metrics.py
hermeskit-1.0.7.data/data/hermeskit/config.yaml
hermeskit-1.0.7.dist-info/LICENSE.txt
hermeskit-1.0.7.dist-info/METADATA
hermeskit-1.0.7.dist-info/WHEEL
hermeskit-1.0.7.dist-info/top_level.txt
hermeskit-1.0.7.dist-info/RECORD
