Metadata-Version: 2.1
Name: hermeskit
Version: 1.0.7
Summary: Credit Scoring Python package
Home-page: https://vinid-team.atlassian.net/wiki/spaces/1/pages/677551034/0.+About+Hermes
Author: HuynhThanhQuan
Author-email: quanht6@onemount.com
Maintainer: HuynhThanhQuan
Maintainer-email: quanht6@onemount.com
License: MIT
Keywords: CreditScoring,Hermes,1MG,CDO
Platform: UNKNOWN
Requires-Python: >=3.7
Requires-Dist: numpy (>=1.18)
Requires-Dist: scikit-learn (>=0.24)
Requires-Dist: pandas (>=1.2)
